{
  "$schema": "https://schema.management.azure.com/schemas/2019-04-01/deploymentTemplate.json#",
  "contentVersion": "1.0.0.0",
  "metadata": {
    "_generator": {
      "name": "bicep",
      "version": "0.23.1.45101",
      "templateHash": "10650131712169379053"
    }
  },
  "parameters": {
    "location": {
      "type": "string",
      "defaultValue": "[resourceGroup().location]"
    },
    "namePrefix": {
      "type": "string",
      "defaultValue": "storage"
    }
  },
  "variables": {
    "storageAccountName": "[format('{0}{1}', parameters('namePrefix'), uniqueString(resourceGroup().id))]",
    "storageAccountSku": "Standard_RAGRS"
  },
  "resources": [
    {
      "type": "Microsoft.Storage/storageAccounts",
      "apiVersion": "2022-05-01",
      "name": "[variables('storageAccountName')]",
      "location": "[parameters('location')]",
      "kind": "StorageV2",
      "sku": {
        "name": "[variables('storageAccountSku')]"
      },
      "properties": {
        "accessTier": "Hot",
        "supportsHttpsTrafficOnly": true
      }
    }
  ],
  "outputs": {
    "storageAccountId": {
      "type": "string",
      "value": "[resourceId('Microsoft.Storage/storageAccounts', variables('storageAccountName'))]"
    }
  }
}